tf/tools/__init__.py
tf/tools/__init__.pyi
tf/tools/pad.py
tf/tools/set.py
tf/tools/typing.py
tf/tools/data/__init__.py
tf/tools/data/datasets.py
tf/tools/sparse/__init__.py
tf/tools/sparse/sparse.py
tf_tools-0.1.6.dist-info/METADATA
tf_tools-0.1.6.dist-info/WHEEL
tf_tools-0.1.6.dist-info/top_level.txt
tf_tools-0.1.6.dist-info/RECORD
